rmg_numerical_integration/__init__.py
rmg_numerical_integration/gaussian_quadrature.py
rmg_numerical_integration/midpoint.py
rmg_numerical_integration/simpson.py
rmg_numerical_integration/trapezoidal.py
rmg_numerical_integration-4.1.dist-info/LICENSE.txt
rmg_numerical_integration-4.1.dist-info/METADATA
rmg_numerical_integration-4.1.dist-info/WHEEL
rmg_numerical_integration-4.1.dist-info/top_level.txt
rmg_numerical_integration-4.1.dist-info/RECORD
