Metadata-Version: 2.1
Name: rmg-numerical-integration
Version: 4.1
Summary: This is a numerical integration package
Author: Roberto Mulas
Author-email: rmulasgarcia@gmail.com
Classifier: Programming Language :: Python :: 3
Classifier: License :: OSI Approved :: MIT License
Classifier: Operating System :: OS Independent
License-File: LICENSE.txt
